{"entityType":2,"citedByExpression":"RId=1772260738","relatedPaperExpression":"Or(Id=2083576834,Id=2257053125,Id=1493426843,Id=2045127536,Id=2044519862,Id=2068078272,Id=2071948233,Id=2590677325,Id=2026972689,Id=1999997905,Id=1596155524,Id=1998623809,Id=2075982893,Id=2039941582,Id=2077359296,Id=2067836716,Id=2592521754,Id=2003650759,Id=2089498317,Id=1620193377,Id=2083576834,Id=2257053125,Id=1493426843,Id=2045127536,Id=2044519862,Id=2068078272,Id=2071948233,Id=2590677325,Id=2026972689,Id=1999997905,Id=1596155524,Id=1998623809,Id=2075982893,Id=2039941582,Id=2077359296,Id=2067836716,Id=2592521754,Id=2003650759,Id=2089498317,Id=1620193377,Id=2083576834,Id=2257053125,Id=1493426843,Id=2045127536,Id=2044519862,Id=2068078272,Id=2071948233,Id=2590677325,Id=2026972689,Id=1999997905,Id=1596155524,Id=1998623809,Id=2075982893,Id=2039941582,Id=2077359296,Id=2067836716,Id=2592521754,Id=2003650759,Id=2089498317,Id=1620193377,Id=2083576834,Id=2257053125,Id=1493426843,Id=2045127536,Id=2044519862,Id=2068078272,Id=2071948233,Id=2590677325,Id=2026972689,Id=1999997905,Id=1596155524,Id=1998623809,Id=2075982893,Id=2039941582,Id=2077359296,Id=2067836716,Id=2592521754,Id=2003650759,Id=2089498317,Id=1620193377)","paperReferencesExpression":"Or(Id=2097246107)","entityExpression":"Id=1772260738","entity":{"fieldsOfStudy":[{"authorCount":0,"id":99844830,"displayName":"Scaling","description":"","publicationCount":0,"publicationCountByYear":[],"citationCnt":0,"citationCountByYear":[],"rank":0.0,"entityType":0},{"authorCount":0,"id":33923547,"displayName":"Mathematics","description":"","publicationCount":0,"publicationCountByYear":[],"citationCnt":0,"citationCountByYear":[],"rank":1.0,"entityType":0},{"authorCount":0,"id":134306372,"displayName":"Mathematical analysis","description":"","publicationCount":0,"publicationCountByYear":[],"citationCnt":0,"citationCountByYear":[],"rank":2.0,"entityType":0},{"authorCount":0,"id":11135259,"displayName":"Length scale","description":"","publicationCount":0,"publicationCountByYear":[],"citationCnt":0,"citationCountByYear":[],"rank":3.0,"entityType":0},{"authorCount":0,"id":120174047,"displayName":"Euclidean distance","description":"","publicationCount":0,"publicationCountByYear":[],"citationCnt":0,"citationCountByYear":[],"rank":4.0,"entityType":0},{"authorCount":0,"id":186603090,"displayName":"Distribution function","description":"","publicationCount":0,"publicationCountByYear":[],"citationCnt":0,"citationCountByYear":[],"rank":5.0,"entityType":0},{"authorCount":0,"id":177562468,"displayName":"Dispersion (optics)","description":"","publicationCount":0,"publicationCountByYear":[],"citationCnt":0,"citationCountByYear":[],"rank":6.0,"entityType":0}],"venueInfo":{"id":2596886445,"entityType":3,"displayName":"arXiv: Statistical Mechanics","volume":"","issue":"","firstPage":"","lastPage":"","publishedDate":"1999-03-03T00:00:00Z"},"sources":[{"sourceType":3,"link":"http://arxiv.org/pdf/cond-mat/9903066.pdf"},{"sourceType":1,"link":"http://adsabs.harvard.edu/abs/1999cond.mat..3066L"},{"sourceType":1,"link":"https://arxiv.org/abs/cond-mat/9903066"}],"authors":[{"currentInstitution":{"authorCount":0,"latitude":0.0,"longitude":0.0,"id":0,"description":"","publicationCount":0,"publicationCountByYear":[],"citationCnt":0,"citationCountByYear":[],"rank":0.0,"entityType":0},"institutions":[{"authorCount":0,"latitude":0.0,"longitude":0.0,"id":0,"description":"","publicationCount":0,"publicationCountByYear":[],"citationCnt":0,"citationCountByYear":[],"rank":0.0,"entityType":0}],"coAuthorCount":0,"hIndex":0.0,"id":2794470509,"displayName":"Youngki Lee","description":"","publicationCount":0,"publicationCountByYear":[],"citationCnt":0,"citationCountByYear":[],"rank":0.0,"entityType":0},{"currentInstitution":{"authorCount":0,"latitude":0.0,"longitude":0.0,"id":0,"description":"","publicationCount":0,"publicationCountByYear":[],"citationCnt":0,"citationCountByYear":[],"rank":0.0,"entityType":0},"institutions":[{"authorCount":0,"latitude":0.0,"longitude":0.0,"id":0,"description":"","publicationCount":0,"publicationCountByYear":[],"citationCnt":0,"citationCountByYear":[],"rank":0.0,"entityType":0}],"coAuthorCount":0,"hIndex":0.0,"id":2100808128,"displayName":"Jose S. Andrade Jr.","description":"","publicationCount":0,"publicationCountByYear":[],"citationCnt":0,"citationCountByYear":[],"rank":0.0,"entityType":0},{"currentInstitution":{"authorCount":0,"latitude":0.0,"longitude":0.0,"id":0,"description":"","publicationCount":0,"publicationCountByYear":[],"citationCnt":0,"citationCountByYear":[],"rank":0.0,"entityType":0},"institutions":[{"authorCount":0,"latitude":0.0,"longitude":0.0,"id":0,"description":"","publicationCount":0,"publicationCountByYear":[],"citationCnt":0,"citationCountByYear":[],"rank":0.0,"entityType":0}],"coAuthorCount":0,"hIndex":0.0,"id":60142663,"displayName":"Sergey V. Buldyrev","description":"","publicationCount":0,"publicationCountByYear":[],"citationCnt":0,"citationCountByYear":[],"rank":0.0,"entityType":0},{"currentInstitution":{"authorCount":0,"latitude":0.0,"longitude":0.0,"id":0,"description":"","publicationCount":0,"publicationCountByYear":[],"citationCnt":0,"citationCountByYear":[],"rank":0.0,"entityType":0},"institutions":[{"authorCount":0,"latitude":0.0,"longitude":0.0,"id":0,"description":"","publicationCount":0,"publicationCountByYear":[],"citationCnt":0,"citationCountByYear":[],"rank":0.0,"entityType":0}],"coAuthorCount":0,"hIndex":0.0,"id":328544140,"displayName":"Nikolay V. Dokholyan","description":"","publicationCount":0,"publicationCountByYear":[],"citationCnt":0,"citationCountByYear":[],"rank":0.0,"entityType":0},{"currentInstitution":{"authorCount":0,"latitude":0.0,"longitude":0.0,"id":0,"description":"","publicationCount":0,"publicationCountByYear":[],"citationCnt":0,"citationCountByYear":[],"rank":0.0,"entityType":0},"institutions":[{"authorCount":0,"latitude":0.0,"longitude":0.0,"id":0,"description":"","publicationCount":0,"publicationCountByYear":[],"citationCnt":0,"citationCountByYear":[],"rank":0.0,"entityType":0}],"coAuthorCount":0,"hIndex":0.0,"id":630663198,"displayName":"Shlomo Havlin","description":"","publicationCount":0,"publicationCountByYear":[],"citationCnt":0,"citationCountByYear":[],"rank":0.0,"entityType":0},{"currentInstitution":{"authorCount":0,"latitude":0.0,"longitude":0.0,"id":0,"description":"","publicationCount":0,"publicationCountByYear":[],"citationCnt":0,"citationCountByYear":[],"rank":0.0,"entityType":0},"institutions":[{"authorCount":0,"latitude":0.0,"longitude":0.0,"id":0,"description":"","publicationCount":0,"publicationCountByYear":[],"citationCnt":0,"citationCountByYear":[],"rank":0.0,"entityType":0}],"coAuthorCount":0,"hIndex":0.0,"id":2475280313,"displayName":"Peter R. King","description":"","publicationCount":0,"publicationCountByYear":[],"citationCnt":0,"citationCountByYear":[],"rank":0.0,"entityType":0},{"currentInstitution":{"authorCount":0,"latitude":0.0,"longitude":0.0,"id":0,"description":"","publicationCount":0,"publicationCountByYear":[],"citationCnt":0,"citationCountByYear":[],"rank":0.0,"entityType":0},"institutions":[{"authorCount":0,"latitude":0.0,"longitude":0.0,"id":0,"description":"","publicationCount":0,"publicationCountByYear":[],"citationCnt":0,"citationCountByYear":[],"rank":0.0,"entityType":0}],"coAuthorCount":0,"hIndex":0.0,"id":2118583891,"displayName":"Gerald Paul","description":"","publicationCount":0,"publicationCountByYear":[],"citationCnt":0,"citationCountByYear":[],"rank":0.0,"entityType":0},{"currentInstitution":{"authorCount":0,"latitude":0.0,"longitude":0.0,"id":111088046,"displayName":"Boston University","description":"","publicationCount":0,"publicationCountByYear":[],"citationCnt":0,"citationCountByYear":[],"rank":0.0,"entityType":0},"institutions":[{"authorCount":0,"latitude":0.0,"longitude":0.0,"id":111088046,"displayName":"Boston University","description":"","publicationCount":0,"publicationCountByYear":[],"citationCnt":0,"citationCountByYear":[],"rank":0.0,"entityType":0}],"coAuthorCount":0,"hIndex":0.0,"id":2420755856,"displayName":"H. Eugene Stanley","description":"","publicationCount":0,"publicationCountByYear":[],"citationCnt":0,"citationCountByYear":[],"rank":0.0,"entityType":0}],"totalAuthorCount":8,"referenceCount":1,"references":[2097246107],"relatedPapers":[2083576834,2257053125,1493426843,2045127536,2044519862,2068078272,2071948233,2590677325,2026972689,1999997905,1596155524,1998623809,2075982893,2039941582,2077359296,2067836716,2592521754,2003650759,2089498317,1620193377,2083576834,2257053125,1493426843,2045127536,2044519862,2068078272,2071948233,2590677325,2026972689,1999997905,1596155524,1998623809,2075982893,2039941582,2077359296,2067836716,2592521754,2003650759,2089498317,1620193377,2083576834,2257053125,1493426843,2045127536,2044519862,2068078272,2071948233,2590677325,2026972689,1999997905,1596155524,1998623809,2075982893,2039941582,2077359296,2067836716,2592521754,2003650759,2089498317,1620193377,2083576834,2257053125,1493426843,2045127536,2044519862,2068078272,2071948233,2590677325,2026972689,1999997905,1596155524,1998623809,2075982893,2039941582,2077359296,2067836716,2592521754,2003650759,2089498317,1620193377],"publicationType":"1","paperResources":[],"id":1772260738,"displayName":"Traveling time and traveling length for flow in porous media","description":"We study traveling time and traveling length for tracer dispersion in porous media. We model porous media by two-dimensional bond percolation, and we model flow by tracer particles driven by a pressure difference between two points separated by Euclidean distance $r$. We find that the minimal traveling time $t_{min}$ scales as $t_{min} \\sim r^{1.40}$, which is different from the scaling of the most probable traveling time, ${\\tilde t} \\sim r^{1.64}$. We also calculate the length of the path corresponding to the minimal traveling time and find $\\ell_{min} \\sim r^{1.13}$ and that the most probable traveling length scales as ${\\tilde \\ell} \\sim r^{1.21}$. We present the relevant distribution functions and scaling relations.","publicationCount":0,"publicationCountByYear":[],"citationCnt":2,"citationCountByYear":[],"rank":22209.0,"entityType":0},"dataVersion":"2019-01-11-prod"}