{"entityType":2,"citedByExpression":"RId=1972608591","relatedPaperExpression":"Or(Id=112956188,Id=2325347651,Id=1630154227,Id=166497774,Id=2039428483,Id=1970655662,Id=2001850246,Id=1989153506,Id=2039101282,Id=1991984235,Id=2159743327,Id=2037874941,Id=2075206601,Id=1526306746,Id=1626372477,Id=2729251808,Id=1517590232,Id=1996372582,Id=2020320444,Id=2085731583,Id=112956188,Id=2325347651,Id=1630154227,Id=166497774,Id=2039428483,Id=1970655662,Id=2001850246,Id=1989153506,Id=2039101282,Id=1991984235,Id=2159743327,Id=2037874941,Id=2075206601,Id=1526306746,Id=1626372477,Id=2729251808,Id=1517590232,Id=1996372582,Id=2020320444,Id=2085731583,Id=112956188,Id=2325347651,Id=1630154227,Id=166497774,Id=2039428483,Id=1970655662,Id=2001850246,Id=1989153506,Id=2039101282,Id=1991984235,Id=2159743327,Id=2037874941,Id=2075206601,Id=1526306746,Id=1626372477,Id=2729251808,Id=1517590232,Id=1996372582,Id=2020320444,Id=2085731583,Id=112956188,Id=2325347651,Id=1630154227,Id=166497774,Id=2039428483,Id=1970655662,Id=2001850246,Id=1989153506,Id=2039101282,Id=1991984235,Id=2159743327,Id=2037874941,Id=2075206601,Id=1526306746,Id=1626372477,Id=2729251808,Id=1517590232,Id=1996372582,Id=2020320444,Id=2085731583)","paperReferencesExpression":"Or(Id=2098045717,Id=2056304260,Id=2360434229,Id=1993239394,Id=1970810217,Id=2022456651,Id=110721923,Id=1992568682)","entityExpression":"Id=1972608591","entity":{"fieldsOfStudy":[{"authorCount":0,"id":154954056,"displayName":"Transverse plane","description":"","publicationCount":0,"publicationCountByYear":[],"citationCnt":0,"citationCountByYear":[],"rank":0.0,"entityType":0},{"authorCount":0,"id":62520636,"displayName":"Quantum mechanics","description":"","publicationCount":0,"publicationCountByYear":[],"citationCnt":0,"citationCountByYear":[],"rank":1.0,"entityType":0},{"authorCount":0,"id":121332964,"displayName":"Physics","description":"","publicationCount":0,"publicationCountByYear":[],"citationCnt":0,"citationCountByYear":[],"rank":2.0,"entityType":0},{"authorCount":0,"id":133386390,"displayName":"Dielectric","description":"","publicationCount":0,"publicationCountByYear":[],"citationCnt":0,"citationCountByYear":[],"rank":3.0,"entityType":0},{"authorCount":0,"id":26873012,"displayName":"Condensed matter physics","description":"","publicationCount":0,"publicationCountByYear":[],"citationCnt":0,"citationCountByYear":[],"rank":4.0,"entityType":0}],"venueInfo":{"id":104875562,"entityType":3,"displayName":"Physics Letters A","volume":"51","issue":"1","firstPage":"33","lastPage":"35","publishedDate":"1975-01-01T00:00:00Z","doi":"10.1016/0375-9601(75)90306-0"},"sources":[{"sourceType":1,"link":"https://www.sciencedirect.com/science/article/pii/0375960175903060"},{"sourceType":1,"link":"http://adsabs.harvard.edu/abs/1975PhLA...51...33H"}],"authors":[{"currentInstitution":{"authorCount":0,"latitude":0.0,"longitude":0.0,"id":13955877,"displayName":"Bar-Ilan University","description":"","publicationCount":0,"publicationCountByYear":[],"citationCnt":0,"citationCountByYear":[],"rank":0.0,"entityType":0},"institutions":[{"authorCount":0,"latitude":0.0,"longitude":0.0,"id":13955877,"displayName":"Bar-Ilan University","description":"","publicationCount":0,"publicationCountByYear":[],"citationCnt":0,"citationCountByYear":[],"rank":0.0,"entityType":0}],"coAuthorCount":0,"hIndex":0.0,"id":630663198,"displayName":"S. Havlin","description":"","publicationCount":0,"publicationCountByYear":[],"citationCnt":0,"citationCountByYear":[],"rank":0.0,"entityType":0},{"currentInstitution":{"authorCount":0,"latitude":0.0,"longitude":0.0,"id":13955877,"displayName":"Bar-Ilan University","description":"","publicationCount":0,"publicationCountByYear":[],"citationCnt":0,"citationCountByYear":[],"rank":0.0,"entityType":0},"institutions":[{"authorCount":0,"latitude":0.0,"longitude":0.0,"id":13955877,"displayName":"Bar-Ilan University","description":"","publicationCount":0,"publicationCountByYear":[],"citationCnt":0,"citationCountByYear":[],"rank":0.0,"entityType":0}],"coAuthorCount":0,"hIndex":0.0,"id":2661208379,"displayName":"E. Litov","description":"","publicationCount":0,"publicationCountByYear":[],"citationCnt":0,"citationCountByYear":[],"rank":0.0,"entityType":0},{"currentInstitution":{"authorCount":0,"latitude":0.0,"longitude":0.0,"id":13955877,"displayName":"Bar-Ilan University","description":"","publicationCount":0,"publicationCountByYear":[],"citationCnt":0,"citationCountByYear":[],"rank":0.0,"entityType":0},"institutions":[{"authorCount":0,"latitude":0.0,"longitude":0.0,"id":13955877,"displayName":"Bar-Ilan University","description":"","publicationCount":0,"publicationCountByYear":[],"citationCnt":0,"citationCountByYear":[],"rank":0.0,"entityType":0}],"coAuthorCount":0,"hIndex":0.0,"id":1974558258,"displayName":"H. Sompolinsky","description":"","publicationCount":0,"publicationCountByYear":[],"citationCnt":0,"citationCountByYear":[],"rank":0.0,"entityType":0}],"totalAuthorCount":3,"referenceCount":8,"references":[2098045717,2056304260,2360434229,1993239394,1970810217,2022456651,110721923,1992568682],"relatedPapers":[112956188,2325347651,1630154227,166497774,2039428483,1970655662,2001850246,1989153506,2039101282,1991984235,2159743327,2037874941,2075206601,1526306746,1626372477,2729251808,1517590232,1996372582,2020320444,2085731583,112956188,2325347651,1630154227,166497774,2039428483,1970655662,2001850246,1989153506,2039101282,1991984235,2159743327,2037874941,2075206601,1526306746,1626372477,2729251808,1517590232,1996372582,2020320444,2085731583,112956188,2325347651,1630154227,166497774,2039428483,1970655662,2001850246,1989153506,2039101282,1991984235,2159743327,2037874941,2075206601,1526306746,1626372477,2729251808,1517590232,1996372582,2020320444,2085731583,112956188,2325347651,1630154227,166497774,2039428483,1970655662,2001850246,1989153506,2039101282,1991984235,2159743327,2037874941,2075206601,1526306746,1626372477,2729251808,1517590232,1996372582,2020320444,2085731583],"publicationType":"1","paperResources":[],"id":1972608591,"displayName":"The transverse dielectric properties of KH2PO4","description":"Abstract   We have measured the transverse dielectric constant of KH 2 PO 4  crystal from liquid N 2  to room temperatures. Extending the Blinc-de Gennes' model in conjunction with a cluster approximation leads to a new independent determination of the Slater-Takagi parameters and improves significantly the fit of the model to the data.","publicationCount":0,"publicationCountByYear":[],"citationCnt":9,"citationCountByYear":[],"rank":23661.0,"entityType":0},"dataVersion":"2019-01-11-prod"}