{"entityType":2,"citedByExpression":"RId=2001405494","relatedPaperExpression":"Or(Id=2145500502,Id=1608882053,Id=2057116804,Id=2155346360,Id=2089409887,Id=2002286553,Id=2017821362,Id=2029501294,Id=2001712064,Id=2028103771,Id=2071602085,Id=2095903124,Id=2122528211,Id=2144106779,Id=2156664872,Id=2169471158,Id=2170453002,Id=8114814,Id=1585871936,Id=2351442912,Id=2145500502,Id=1608882053,Id=2057116804,Id=2155346360,Id=2089409887,Id=2002286553,Id=2017821362,Id=2029501294,Id=2001712064,Id=2028103771,Id=2071602085,Id=2095903124,Id=2122528211,Id=2144106779,Id=2156664872,Id=2169471158,Id=2170453002,Id=8114814,Id=1585871936,Id=2351442912,Id=2145500502,Id=1608882053,Id=2057116804,Id=2155346360,Id=2089409887,Id=2002286553,Id=2017821362,Id=2029501294,Id=2001712064,Id=2028103771,Id=2071602085,Id=2095903124,Id=2122528211,Id=2144106779,Id=2156664872,Id=2169471158,Id=2170453002,Id=8114814,Id=1585871936,Id=2351442912,Id=2145500502,Id=1608882053,Id=2057116804,Id=2155346360,Id=2089409887,Id=2002286553,Id=2017821362,Id=2029501294,Id=2001712064,Id=2028103771,Id=2071602085,Id=2095903124,Id=2122528211,Id=2144106779,Id=2156664872,Id=2169471158,Id=2170453002,Id=8114814,Id=1585871936,Id=2351442912)","paperReferencesExpression":"Or(Id=1608882053,Id=1607313394)","entityExpression":"Id=2001405494","entity":{"fieldsOfStudy":[{"authorCount":0,"id":91602232,"displayName":"Volatility (finance)","description":"","publicationCount":0,"publicationCountByYear":[],"citationCnt":0,"citationCountByYear":[],"rank":0.0,"entityType":0},{"authorCount":0,"id":2780299701,"displayName":"Stock market","description":"","publicationCount":0,"publicationCountByYear":[],"citationCnt":0,"citationCountByYear":[],"rank":1.0,"entityType":0},{"authorCount":0,"id":99844830,"displayName":"Scaling","description":"","publicationCount":0,"publicationCountByYear":[],"citationCnt":0,"citationCountByYear":[],"rank":2.0,"entityType":0},{"authorCount":0,"id":197055811,"displayName":"Probability density function","description":"","publicationCount":0,"publicationCountByYear":[],"citationCnt":0,"citationCountByYear":[],"rank":3.0,"entityType":0},{"authorCount":0,"id":87040749,"displayName":"Power law","description":"","publicationCount":0,"publicationCountByYear":[],"citationCnt":0,"citationCountByYear":[],"rank":4.0,"entityType":0},{"authorCount":0,"id":121332964,"displayName":"Physics","description":"","publicationCount":0,"publicationCountByYear":[],"citationCnt":0,"citationCountByYear":[],"rank":5.0,"entityType":0},{"authorCount":0,"id":193445137,"displayName":"Market capitalization","description":"","publicationCount":0,"publicationCountByYear":[],"citationCnt":0,"citationCountByYear":[],"rank":6.0,"entityType":0},{"authorCount":0,"id":10138342,"displayName":"Finance","description":"","publicationCount":0,"publicationCountByYear":[],"citationCnt":0,"citationCountByYear":[],"rank":7.0,"entityType":0},{"authorCount":0,"id":186603090,"displayName":"Distribution function","description":"","publicationCount":0,"publicationCountByYear":[],"citationCnt":0,"citationCountByYear":[],"rank":8.0,"entityType":0},{"authorCount":0,"id":44492722,"displayName":"Conditional probability","description":"","publicationCount":0,"publicationCountByYear":[],"citationCnt":0,"citationCountByYear":[],"rank":9.0,"entityType":0}],"venueInfo":{"id":35412551,"entityType":3,"displayName":"Physical Review E","volume":"84","issue":"4","firstPage":"46112","lastPage":"","publishedDate":"2011-10-24T00:00:00Z","doi":"10.1103/PhysRevE.84.046112"},"sources":[{"sourceType":3,"link":"https://arxiv.org/pdf/1106.1415"},{"sourceType":1,"link":"https://www.ncbi.nlm.nih.gov/pubmed/22181232"},{"sourceType":1,"link":"http://adsabs.harvard.edu/abs/2011arXiv1106.1415L"},{"sourceType":1,"link":"https://arxiv.org/abs/1106.1415v1"},{"sourceType":1,"link":"https://ideas.repec.org/p/arx/papers/1106.1415.html"},{"sourceType":1,"link":"https://EconPapers.repec.org/RePEc:arx:papers:1106.1415"}],"authors":[{"currentInstitution":{"authorCount":0,"latitude":0.0,"longitude":0.0,"id":0,"description":"","publicationCount":0,"publicationCountByYear":[],"citationCnt":0,"citationCountByYear":[],"rank":0.0,"entityType":0},"institutions":[{"authorCount":0,"latitude":0.0,"longitude":0.0,"id":0,"description":"","publicationCount":0,"publicationCountByYear":[],"citationCnt":0,"citationCountByYear":[],"rank":0.0,"entityType":0}],"coAuthorCount":0,"hIndex":0.0,"id":2576955417,"displayName":"Wei Li","description":"","publicationCount":0,"publicationCountByYear":[],"citationCnt":0,"citationCountByYear":[],"rank":0.0,"entityType":0},{"currentInstitution":{"authorCount":0,"latitude":0.0,"longitude":0.0,"id":0,"description":"","publicationCount":0,"publicationCountByYear":[],"citationCnt":0,"citationCountByYear":[],"rank":0.0,"entityType":0},"institutions":[{"authorCount":0,"latitude":0.0,"longitude":0.0,"id":0,"description":"","publicationCount":0,"publicationCountByYear":[],"citationCnt":0,"citationCountByYear":[],"rank":0.0,"entityType":0}],"coAuthorCount":0,"hIndex":0.0,"id":2147924177,"displayName":"Fengzhong Wang","description":"","publicationCount":0,"publicationCountByYear":[],"citationCnt":0,"citationCountByYear":[],"rank":0.0,"entityType":0},{"currentInstitution":{"authorCount":0,"latitude":0.0,"longitude":0.0,"id":0,"description":"","publicationCount":0,"publicationCountByYear":[],"citationCnt":0,"citationCountByYear":[],"rank":0.0,"entityType":0},"institutions":[{"authorCount":0,"latitude":0.0,"longitude":0.0,"id":0,"description":"","publicationCount":0,"publicationCountByYear":[],"citationCnt":0,"citationCountByYear":[],"rank":0.0,"entityType":0}],"coAuthorCount":0,"hIndex":0.0,"id":630663198,"displayName":"Shlomo Havlin","description":"","publicationCount":0,"publicationCountByYear":[],"citationCnt":0,"citationCountByYear":[],"rank":0.0,"entityType":0},{"currentInstitution":{"authorCount":0,"latitude":0.0,"longitude":0.0,"id":0,"description":"","publicationCount":0,"publicationCountByYear":[],"citationCnt":0,"citationCountByYear":[],"rank":0.0,"entityType":0},"institutions":[{"authorCount":0,"latitude":0.0,"longitude":0.0,"id":0,"description":"","publicationCount":0,"publicationCountByYear":[],"citationCnt":0,"citationCountByYear":[],"rank":0.0,"entityType":0}],"coAuthorCount":0,"hIndex":0.0,"id":2420755856,"displayName":"H. Eugene Stanley","description":"","publicationCount":0,"publicationCountByYear":[],"citationCnt":0,"citationCountByYear":[],"rank":0.0,"entityType":0}],"totalAuthorCount":4,"referenceCount":2,"references":[1608882053,1607313394],"relatedPapers":[2145500502,1608882053,2057116804,2155346360,2089409887,2002286553,2017821362,2029501294,2001712064,2028103771,2071602085,2095903124,2122528211,2144106779,2156664872,2169471158,2170453002,8114814,1585871936,2351442912,2145500502,1608882053,2057116804,2155346360,2089409887,2002286553,2017821362,2029501294,2001712064,2028103771,2071602085,2095903124,2122528211,2144106779,2156664872,2169471158,2170453002,8114814,1585871936,2351442912,2145500502,1608882053,2057116804,2155346360,2089409887,2002286553,2017821362,2029501294,2001712064,2028103771,2071602085,2095903124,2122528211,2144106779,2156664872,2169471158,2170453002,8114814,1585871936,2351442912,2145500502,1608882053,2057116804,2155346360,2089409887,2002286553,2017821362,2029501294,2001712064,2028103771,2071602085,2095903124,2122528211,2144106779,2156664872,2169471158,2170453002,8114814,1585871936,2351442912],"publicationType":"1","paperResources":[],"id":2001405494,"displayName":"Financial factor influence on scaling and memory of trading volume in stock market","description":"We study the daily trading volume volatility of 17,197 stocks in the U.S. stock markets during the period 1989--2008 and analyze the time return intervals $\\tau$ between volume volatilities above a given threshold q. For different thresholds q, the probability density function P_q(\\tau) scales with mean interval as P_q(\\tau)= ^{-1}f(\\tau/ ) and the tails of the scaling function can be well approximated by a power-law f(x)~x^{-\\gamma}. We also study the relation between the form of the distribution function P_q(\\tau) and several financial factors: stock lifetime, market capitalization, volume, and trading value. We find a systematic tendency of P_q(\\tau) associated with these factors, suggesting a multi-scaling feature in the volume return intervals. We analyze the conditional probability P_q(\\tau|\\tau_0) for $\\tau$ following a certain interval \\tau_0, and find that P_q(\\tau|\\tau_0) depends on \\tau_0 such that immediately following a short/long return interval a second short/long return interval tends to occur. We also find indications that there is a long-term correlation in the daily volume volatility. We compare our results to those found earlier for price volatility.","publicationCount":0,"publicationCountByYear":[],"citationCnt":25,"citationCountByYear":[],"rank":20451.0,"entityType":0},"dataVersion":"2019-01-11-prod"}