{"entityType":2,"citedByExpression":"RId=2035673570","relatedPaperExpression":"Or(Id=1968164782,Id=2157480076,Id=2008620264,Id=1879056329,Id=2149527103,Id=1679955203,Id=1650742658,Id=2065769502,Id=2112090702,Id=1618470073,Id=1555596743,Id=2005641459,Id=2034714338,Id=2050401089,Id=2083420849,Id=2070207525,Id=2113188272,Id=1980423440,Id=1985909783,Id=1989400610,Id=1968164782,Id=2157480076,Id=2008620264,Id=1879056329,Id=2149527103,Id=1679955203,Id=1650742658,Id=2065769502,Id=2112090702,Id=1618470073,Id=1555596743,Id=2005641459,Id=2034714338,Id=2050401089,Id=2083420849,Id=2070207525,Id=2113188272,Id=1980423440,Id=1985909783,Id=1989400610,Id=1968164782,Id=2157480076,Id=2008620264,Id=1879056329,Id=2149527103,Id=1679955203,Id=1650742658,Id=2065769502,Id=2112090702,Id=1618470073,Id=1555596743,Id=2005641459,Id=2034714338,Id=2050401089,Id=2083420849,Id=2070207525,Id=2113188272,Id=1980423440,Id=1985909783,Id=1989400610,Id=1968164782,Id=2157480076,Id=2008620264,Id=1879056329,Id=2149527103,Id=1679955203,Id=1650742658,Id=2065769502,Id=2112090702,Id=1618470073,Id=1555596743,Id=2005641459,Id=2034714338,Id=2050401089,Id=2083420849,Id=2070207525,Id=2113188272,Id=1980423440,Id=1985909783,Id=1989400610)","paperReferencesExpression":"Or(Id=1875112053,Id=2000042664,Id=2065769502,Id=1968164782,Id=2018045523,Id=41377044,Id=2030539428,Id=2149527103,Id=2096526352,Id=1989400610,Id=2157480076,Id=2005641459,Id=2162808198,Id=1679955203,Id=1985909783,Id=1578019527,Id=1967510236,Id=2034714338,Id=1991098816,Id=1650742658,Id=2026808254,Id=2080397156,Id=2048376619,Id=2004670325,Id=2052055672,Id=106398726,Id=1915994693,Id=2055276689,Id=2087129091,Id=1977855336,Id=2063729812)","entityExpression":"Id=2035673570","entity":{"fieldsOfStudy":[{"authorCount":0,"id":99844830,"displayName":"Scaling","description":"","publicationCount":0,"publicationCountByYear":[],"citationCnt":0,"citationCountByYear":[],"rank":0.0,"entityType":0},{"authorCount":0,"id":97970142,"displayName":"Robustness (computer science)","description":"","publicationCount":0,"publicationCountByYear":[],"citationCnt":0,"citationCountByYear":[],"rank":1.0,"entityType":0},{"authorCount":0,"id":120314980,"displayName":"Distributed computing","description":"","publicationCount":0,"publicationCountByYear":[],"citationCnt":0,"citationCountByYear":[],"rank":2.0,"entityType":0},{"authorCount":0,"id":124101348,"displayName":"Data mining","description":"","publicationCount":0,"publicationCountByYear":[],"citationCnt":0,"citationCountByYear":[],"rank":3.0,"entityType":0},{"authorCount":0,"id":41008148,"displayName":"Computer science","description":"","publicationCount":0,"publicationCountByYear":[],"citationCnt":0,"citationCountByYear":[],"rank":4.0,"entityType":0},{"authorCount":0,"id":119323957,"displayName":"Cascading failure","description":"","publicationCount":0,"publicationCountByYear":[],"citationCnt":0,"citationCountByYear":[],"rank":5.0,"entityType":0},{"authorCount":0,"id":117045392,"displayName":"Betweenness centrality","description":"","publicationCount":0,"publicationCountByYear":[],"citationCnt":0,"citationCountByYear":[],"rank":6.0,"entityType":0},{"authorCount":0,"id":50644808,"displayName":"Artificial neural network","description":"","publicationCount":0,"publicationCountByYear":[],"citationCnt":0,"citationCountByYear":[],"rank":7.0,"entityType":0}],"venueInfo":{"id":196734849,"entityType":3,"displayName":"Scientific Reports","volume":"3","issue":"1","firstPage":"1969","lastPage":"1969","publishedDate":"2013-12-01T00:00:00Z","doi":"10.1038/srep01969"},"sources":[{"sourceType":3,"link":"http://havlin.biu.ac.il/PS/Towards%20designing%20robust%20coupled%20networks.pdf"},{"sourceType":3,"link":"http://dspace.mit.edu/openaccess-disseminate/1721.1/88220"},{"sourceType":3,"link":"https://arxiv.org/pdf/1106.3234"},{"sourceType":1,"link":"https://arxiv.org/abs/1106.3234"},{"sourceType":1,"link":"http://www.nature.com/srep/2013/130611/srep01969/fig_tab/srep01969_F4.html"},{"sourceType":1,"link":"https://www.ncbi.nlm.nih.gov/pubmed/23752705"},{"sourceType":1,"link":"http://europepmc.org/articles/PMC3678138"},{"sourceType":1,"link":"http://adsabs.harvard.edu/abs/2011arXiv1106.3234S"},{"sourceType":1,"link":"https://dspace.mit.edu/handle/1721.1/88220"},{"sourceType":0,"link":"http://europepmc.org/abstract/MED/23752705"},{"sourceType":0,"link":"http://www.nature.com/articles/srep01969.pdf"}],"authors":[{"currentInstitution":{"authorCount":0,"latitude":0.0,"longitude":0.0,"id":0,"description":"","publicationCount":0,"publicationCountByYear":[],"citationCnt":0,"citationCountByYear":[],"rank":0.0,"entityType":0},"institutions":[{"authorCount":0,"latitude":0.0,"longitude":0.0,"id":0,"description":"","publicationCount":0,"publicationCountByYear":[],"citationCnt":0,"citationCountByYear":[],"rank":0.0,"entityType":0}],"coAuthorCount":0,"hIndex":0.0,"id":2274213919,"displayName":"Christian M. Schneider","description":"","publicationCount":0,"publicationCountByYear":[],"citationCnt":0,"citationCountByYear":[],"rank":0.0,"entityType":0},{"currentInstitution":{"authorCount":0,"latitude":0.0,"longitude":0.0,"id":0,"description":"","publicationCount":0,"publicationCountByYear":[],"citationCnt":0,"citationCountByYear":[],"rank":0.0,"entityType":0},"institutions":[{"authorCount":0,"latitude":0.0,"longitude":0.0,"id":0,"description":"","publicationCount":0,"publicationCountByYear":[],"citationCnt":0,"citationCountByYear":[],"rank":0.0,"entityType":0}],"coAuthorCount":0,"hIndex":0.0,"id":2687656910,"displayName":"Nuri Yazdani","description":"","publicationCount":0,"publicationCountByYear":[],"citationCnt":0,"citationCountByYear":[],"rank":0.0,"entityType":0},{"currentInstitution":{"authorCount":0,"latitude":0.0,"longitude":0.0,"id":0,"description":"","publicationCount":0,"publicationCountByYear":[],"citationCnt":0,"citationCountByYear":[],"rank":0.0,"entityType":0},"institutions":[{"authorCount":0,"latitude":0.0,"longitude":0.0,"id":0,"description":"","publicationCount":0,"publicationCountByYear":[],"citationCnt":0,"citationCountByYear":[],"rank":0.0,"entityType":0}],"coAuthorCount":0,"hIndex":0.0,"id":2095693673,"displayName":"Nuno A. M. Araújo","description":"","publicationCount":0,"publicationCountByYear":[],"citationCnt":0,"citationCountByYear":[],"rank":0.0,"entityType":0},{"currentInstitution":{"authorCount":0,"latitude":0.0,"longitude":0.0,"id":0,"description":"","publicationCount":0,"publicationCountByYear":[],"citationCnt":0,"citationCountByYear":[],"rank":0.0,"entityType":0},"institutions":[{"authorCount":0,"latitude":0.0,"longitude":0.0,"id":0,"description":"","publicationCount":0,"publicationCountByYear":[],"citationCnt":0,"citationCountByYear":[],"rank":0.0,"entityType":0}],"coAuthorCount":0,"hIndex":0.0,"id":630663198,"displayName":"Shlomo Havlin","description":"","publicationCount":0,"publicationCountByYear":[],"citationCnt":0,"citationCountByYear":[],"rank":0.0,"entityType":0},{"currentInstitution":{"authorCount":0,"latitude":0.0,"longitude":0.0,"id":0,"description":"","publicationCount":0,"publicationCountByYear":[],"citationCnt":0,"citationCountByYear":[],"rank":0.0,"entityType":0},"institutions":[{"authorCount":0,"latitude":0.0,"longitude":0.0,"id":0,"description":"","publicationCount":0,"publicationCountByYear":[],"citationCnt":0,"citationCountByYear":[],"rank":0.0,"entityType":0}],"coAuthorCount":0,"hIndex":0.0,"id":2402136119,"displayName":"Hans J. Herrmann","description":"","publicationCount":0,"publicationCountByYear":[],"citationCnt":0,"citationCountByYear":[],"rank":0.0,"entityType":0}],"totalAuthorCount":5,"referenceCount":31,"references":[1875112053,2000042664,2065769502,1968164782,2018045523,41377044,2030539428,2149527103,2096526352,1989400610,2157480076,2005641459,2162808198,1679955203,1985909783,1578019527,1967510236,2034714338,1991098816,1650742658,2026808254,2080397156,2048376619,2004670325,2052055672,106398726,1915994693,2055276689,2087129091,1977855336,2063729812],"relatedPapers":[1968164782,2157480076,2008620264,1879056329,2149527103,1679955203,1650742658,2065769502,2112090702,1618470073,1555596743,2005641459,2034714338,2050401089,2083420849,2070207525,2113188272,1980423440,1985909783,1989400610,1968164782,2157480076,2008620264,1879056329,2149527103,1679955203,1650742658,2065769502,2112090702,1618470073,1555596743,2005641459,2034714338,2050401089,2083420849,2070207525,2113188272,1980423440,1985909783,1989400610,1968164782,2157480076,2008620264,1879056329,2149527103,1679955203,1650742658,2065769502,2112090702,1618470073,1555596743,2005641459,2034714338,2050401089,2083420849,2070207525,2113188272,1980423440,1985909783,1989400610,1968164782,2157480076,2008620264,1879056329,2149527103,1679955203,1650742658,2065769502,2112090702,1618470073,1555596743,2005641459,2034714338,2050401089,2083420849,2070207525,2113188272,1980423440,1985909783,1989400610],"publicationType":"1","paperResources":[],"id":2035673570,"displayName":"Towards designing robust coupled networks","description":"Natural and technological interdependent systems have been shown to be highly vulnerable due to cascading failures and an abrupt collapse of global connectivity under initial failure. Mitigating the risk by partial disconnection endangers their functionality. Here we propose a systematic strategy of selecting a minimum number of autonomous nodes that guarantee a smooth transition in robustness. Our method which is based on betweenness is tested on various examples including the famous 2003 electrical blackout of Italy. We show that, with this strategy, the necessary number of autonomous nodes can be reduced by a factor of five compared to a random choice. We also find that the transition to abrupt collapse follows tricritical scaling characterized by a set of exponents which is independent on the protection strategy.","publicationCount":0,"publicationCountByYear":[],"citationCnt":169,"citationCountByYear":[],"rank":18769.0,"entityType":0},"dataVersion":"2019-01-11-prod"}