{"entityType":2,"citedByExpression":"RId=2103827955","relatedPaperExpression":"Or(Id=2151749474,Id=2136262262,Id=2765539697,Id=2073395065,Id=2382208441,Id=2584192798,Id=2000240635,Id=1992874532,Id=2076383671,Id=2042432619,Id=2117509899,Id=1486937721,Id=2312874684,Id=2038653013,Id=2569516398,Id=2161164433,Id=2045575893,Id=2115207992,Id=1981767959,Id=2055887490,Id=2151749474,Id=2136262262,Id=2765539697,Id=2073395065,Id=2382208441,Id=2584192798,Id=2000240635,Id=1992874532,Id=2076383671,Id=2042432619,Id=2117509899,Id=1486937721,Id=2312874684,Id=2038653013,Id=2569516398,Id=2161164433,Id=2045575893,Id=2115207992,Id=1981767959,Id=2055887490,Id=2151749474,Id=2136262262,Id=2765539697,Id=2073395065,Id=2382208441,Id=2584192798,Id=2000240635,Id=1992874532,Id=2076383671,Id=2042432619,Id=2117509899,Id=1486937721,Id=2312874684,Id=2038653013,Id=2569516398,Id=2161164433,Id=2045575893,Id=2115207992,Id=1981767959,Id=2055887490,Id=2151749474,Id=2136262262,Id=2765539697,Id=2073395065,Id=2382208441,Id=2584192798,Id=2000240635,Id=1992874532,Id=2076383671,Id=2042432619,Id=2117509899,Id=1486937721,Id=2312874684,Id=2038653013,Id=2569516398,Id=2161164433,Id=2045575893,Id=2115207992,Id=1981767959,Id=2055887490)","paperReferencesExpression":"Or(Id=1886211768,Id=2139841187,Id=1979158913,Id=2142703753,Id=2138064535,Id=2146982119,Id=2108144722,Id=2097045245,Id=2171028594,Id=1969789063,Id=2049105549,Id=2101660588,Id=1972496975,Id=2143819964,Id=2171688797,Id=2049183416,Id=1562441992,Id=20141004,Id=2166527315,Id=1598756928,Id=1978490421,Id=1976841314)","entityExpression":"Id=2103827955","entity":{"fieldsOfStudy":[{"authorCount":0,"id":205545832,"displayName":"Young adult","description":"","publicationCount":0,"publicationCountByYear":[],"citationCnt":0,"citationCountByYear":[],"rank":0.0,"entityType":0},{"authorCount":0,"id":159047783,"displayName":"Virology","description":"","publicationCount":0,"publicationCountByYear":[],"citationCnt":0,"citationCountByYear":[],"rank":1.0,"entityType":0},{"authorCount":0,"id":89623803,"displayName":"Pandemic","description":"","publicationCount":0,"publicationCountByYear":[],"citationCnt":0,"citationCountByYear":[],"rank":2.0,"entityType":0},{"authorCount":0,"id":116675565,"displayName":"Outbreak","description":"","publicationCount":0,"publicationCountByYear":[],"citationCnt":0,"citationCountByYear":[],"rank":3.0,"entityType":0},{"authorCount":0,"id":179755657,"displayName":"Mortality rate","description":"","publicationCount":0,"publicationCountByYear":[],"citationCnt":0,"citationCountByYear":[],"rank":4.0,"entityType":0},{"authorCount":0,"id":71924100,"displayName":"Medicine","description":"","publicationCount":0,"publicationCountByYear":[],"citationCnt":0,"citationCountByYear":[],"rank":5.0,"entityType":0},{"authorCount":0,"id":2777546802,"displayName":"Influenza A virus","description":"","publicationCount":0,"publicationCountByYear":[],"citationCnt":0,"citationCountByYear":[],"rank":6.0,"entityType":0},{"authorCount":0,"id":203014093,"displayName":"Immunology","description":"","publicationCount":0,"publicationCountByYear":[],"citationCnt":0,"citationCountByYear":[],"rank":7.0,"entityType":0},{"authorCount":0,"id":192805744,"displayName":"Human mortality from H5N1","description":"","publicationCount":0,"publicationCountByYear":[],"citationCnt":0,"citationCountByYear":[],"rank":8.0,"entityType":0}],"venueInfo":{"id":93534766,"entityType":3,"displayName":"Influenza and Other Respiratory Viruses","volume":"4","issue":"4","firstPage":"205","lastPage":"212","publishedDate":"2010-03-22T00:00:00Z","doi":"10.1111/j.1750-2659.2010.00137.x"},"sources":[{"sourceType":1,"link":"https://www.ncbi.nlm.nih.gov/pubmed/20836795"},{"sourceType":1,"link":"http://europepmc.org/articles/PMC2951388"},{"sourceType":1,"link":"https://www.cabdirect.org/cabdirect/abstract/20103248162"},{"sourceType":1,"link":"http://onlinelibrary.wiley.com/doi/10.1111/j.1750-2659.2010.00137.x/full"},{"sourceType":1,"link":"http://city.milwaukee.gov/ImageLibrary/Groups/healthAuthors/ADMIN/PDFs/ELT-ARTICLES/2010LofgrenFluinWI.PDF"},{"sourceType":0,"link":"http://doi.wiley.com/10.1111/j.1750-2659.2010.00137.x"}],"authors":[{"currentInstitution":{"authorCount":0,"latitude":0.0,"longitude":0.0,"id":114027177,"displayName":"University of North Carolina at Chapel Hill","description":"","publicationCount":0,"publicationCountByYear":[],"citationCnt":0,"citationCountByYear":[],"rank":0.0,"entityType":0},"institutions":[{"authorCount":0,"latitude":0.0,"longitude":0.0,"id":114027177,"displayName":"University of North Carolina at Chapel Hill","description":"","publicationCount":0,"publicationCountByYear":[],"citationCnt":0,"citationCountByYear":[],"rank":0.0,"entityType":0}],"coAuthorCount":0,"hIndex":0.0,"id":2091837159,"displayName":"Eric T. Lofgren","description":"","publicationCount":0,"publicationCountByYear":[],"citationCnt":0,"citationCountByYear":[],"rank":0.0,"entityType":0},{"currentInstitution":{"authorCount":0,"latitude":0.0,"longitude":0.0,"id":121934306,"displayName":"Tufts University","description":"","publicationCount":0,"publicationCountByYear":[],"citationCnt":0,"citationCountByYear":[],"rank":0.0,"entityType":0},"institutions":[{"authorCount":0,"latitude":0.0,"longitude":0.0,"id":121934306,"displayName":"Tufts University","description":"","publicationCount":0,"publicationCountByYear":[],"citationCnt":0,"citationCountByYear":[],"rank":0.0,"entityType":0}],"coAuthorCount":0,"hIndex":0.0,"id":2140846822,"displayName":"Julia B. Wenger","description":"","publicationCount":0,"publicationCountByYear":[],"citationCnt":0,"citationCountByYear":[],"rank":0.0,"entityType":0},{"currentInstitution":{"authorCount":0,"latitude":0.0,"longitude":0.0,"id":102322142,"displayName":"Rutgers University","description":"","publicationCount":0,"publicationCountByYear":[],"citationCnt":0,"citationCountByYear":[],"rank":0.0,"entityType":0},"institutions":[{"authorCount":0,"latitude":0.0,"longitude":0.0,"id":102322142,"displayName":"Rutgers University","description":"","publicationCount":0,"publicationCountByYear":[],"citationCnt":0,"citationCountByYear":[],"rank":0.0,"entityType":0},{"authorCount":0,"latitude":0.0,"longitude":0.0,"id":2799411422,"displayName":"Center for Discrete Mathematics and Theoretical Computer Science","description":"","publicationCount":0,"publicationCountByYear":[],"citationCnt":0,"citationCountByYear":[],"rank":0.0,"entityType":0}],"coAuthorCount":0,"hIndex":0.0,"id":705403811,"displayName":"Nina H. Fefferman","description":"","publicationCount":0,"publicationCountByYear":[],"citationCnt":0,"citationCountByYear":[],"rank":0.0,"entityType":0},{"currentInstitution":{"authorCount":0,"latitude":0.0,"longitude":0.0,"id":0,"displayName":"City of Milwaukee Health Department, Milwaukee, WI, USA.","description":"","publicationCount":0,"publicationCountByYear":[],"citationCnt":0,"citationCountByYear":[],"rank":0.0,"entityType":0},"institutions":[{"authorCount":0,"latitude":0.0,"longitude":0.0,"id":0,"displayName":"City of Milwaukee Health Department, Milwaukee, WI, USA.","description":"","publicationCount":0,"publicationCountByYear":[],"citationCnt":0,"citationCountByYear":[],"rank":0.0,"entityType":0}],"coAuthorCount":0,"hIndex":0.0,"id":2651578212,"displayName":"David Bina","description":"","publicationCount":0,"publicationCountByYear":[],"citationCnt":0,"citationCountByYear":[],"rank":0.0,"entityType":0},{"currentInstitution":{"authorCount":0,"latitude":0.0,"longitude":0.0,"id":0,"displayName":"City of Milwaukee Health Department, Milwaukee, WI, USA.","description":"","publicationCount":0,"publicationCountByYear":[],"citationCnt":0,"citationCountByYear":[],"rank":0.0,"entityType":0},"institutions":[{"authorCount":0,"latitude":0.0,"longitude":0.0,"id":0,"displayName":"City of Milwaukee Health Department, Milwaukee, WI, USA.","description":"","publicationCount":0,"publicationCountByYear":[],"citationCnt":0,"citationCountByYear":[],"rank":0.0,"entityType":0}],"coAuthorCount":0,"hIndex":0.0,"id":2038369357,"displayName":"Steve Gradus","description":"","publicationCount":0,"publicationCountByYear":[],"citationCnt":0,"citationCountByYear":[],"rank":0.0,"entityType":0},{"currentInstitution":{"authorCount":0,"latitude":0.0,"longitude":0.0,"id":0,"displayName":"City of Milwaukee Health Department, Milwaukee, WI, USA.","description":"","publicationCount":0,"publicationCountByYear":[],"citationCnt":0,"citationCountByYear":[],"rank":0.0,"entityType":0},"institutions":[{"authorCount":0,"latitude":0.0,"longitude":0.0,"id":0,"displayName":"City of Milwaukee Health Department, Milwaukee, WI, USA.","description":"","publicationCount":0,"publicationCountByYear":[],"citationCnt":0,"citationCountByYear":[],"rank":0.0,"entityType":0}],"coAuthorCount":0,"hIndex":0.0,"id":2108840573,"displayName":"Sanjib Bhattacharyya","description":"","publicationCount":0,"publicationCountByYear":[],"citationCnt":0,"citationCountByYear":[],"rank":0.0,"entityType":0},{"currentInstitution":{"authorCount":0,"latitude":0.0,"longitude":0.0,"id":166722992,"displayName":"University of Massachusetts Medical School","description":"","publicationCount":0,"publicationCountByYear":[],"citationCnt":0,"citationCountByYear":[],"rank":0.0,"entityType":0},"institutions":[{"authorCount":0,"latitude":0.0,"longitude":0.0,"id":166722992,"displayName":"University of Massachusetts Medical School","description":"","publicationCount":0,"publicationCountByYear":[],"citationCnt":0,"citationCountByYear":[],"rank":0.0,"entityType":0}],"coAuthorCount":0,"hIndex":0.0,"id":2026322238,"displayName":"Yuri N. Naumov","description":"","publicationCount":0,"publicationCountByYear":[],"citationCnt":0,"citationCountByYear":[],"rank":0.0,"entityType":0},{"currentInstitution":{"authorCount":0,"latitude":0.0,"longitude":0.0,"id":0,"displayName":"Blood Research Institute, BloodCenter of Wisconsin, Milwaukee, WI, USA.","description":"","publicationCount":0,"publicationCountByYear":[],"citationCnt":0,"citationCountByYear":[],"rank":0.0,"entityType":0},"institutions":[{"authorCount":0,"latitude":0.0,"longitude":0.0,"id":0,"displayName":"Blood Research Institute, BloodCenter of Wisconsin, Milwaukee, WI, USA.","description":"","publicationCount":0,"publicationCountByYear":[],"citationCnt":0,"citationCountByYear":[],"rank":0.0,"entityType":0}],"coAuthorCount":0,"hIndex":0.0,"id":2187230080,"displayName":"Jack Gorski","description":"","publicationCount":0,"publicationCountByYear":[],"citationCnt":0,"citationCountByYear":[],"rank":0.0,"entityType":0},{"currentInstitution":{"authorCount":0,"latitude":0.0,"longitude":0.0,"id":121934306,"displayName":"Tufts University","description":"","publicationCount":0,"publicationCountByYear":[],"citationCnt":0,"citationCountByYear":[],"rank":0.0,"entityType":0},"institutions":[{"authorCount":0,"latitude":0.0,"longitude":0.0,"id":121934306,"displayName":"Tufts University","description":"","publicationCount":0,"publicationCountByYear":[],"citationCnt":0,"citationCountByYear":[],"rank":0.0,"entityType":0}],"coAuthorCount":0,"hIndex":0.0,"id":2059851128,"displayName":"Elena N. Naumova","description":"","publicationCount":0,"publicationCountByYear":[],"citationCnt":0,"citationCountByYear":[],"rank":0.0,"entityType":0}],"totalAuthorCount":9,"referenceCount":22,"references":[1886211768,2139841187,1979158913,2142703753,2138064535,2146982119,2108144722,2097045245,2171028594,1969789063,2049105549,2101660588,1972496975,2143819964,2171688797,2049183416,1562441992,20141004,2166527315,1598756928,1978490421,1976841314],"relatedPapers":[2151749474,2136262262,2765539697,2073395065,2382208441,2584192798,2000240635,1992874532,2076383671,2042432619,2117509899,1486937721,2312874684,2038653013,2569516398,2161164433,2045575893,2115207992,1981767959,2055887490,2151749474,2136262262,2765539697,2073395065,2382208441,2584192798,2000240635,1992874532,2076383671,2042432619,2117509899,1486937721,2312874684,2038653013,2569516398,2161164433,2045575893,2115207992,1981767959,2055887490,2151749474,2136262262,2765539697,2073395065,2382208441,2584192798,2000240635,1992874532,2076383671,2042432619,2117509899,1486937721,2312874684,2038653013,2569516398,2161164433,2045575893,2115207992,1981767959,2055887490,2151749474,2136262262,2765539697,2073395065,2382208441,2584192798,2000240635,1992874532,2076383671,2042432619,2117509899,1486937721,2312874684,2038653013,2569516398,2161164433,2045575893,2115207992,1981767959,2055887490],"publicationType":"1","paperResources":[],"id":2103827955,"displayName":"Disproportional effects in populations of concern for pandemic influenza: insights from seasonal epidemics in Wisconsin, 1967–2004","description":"Please cite this paper as: Lofgren et al. (2010) Disproportional effects in populations of concern for pandemic influenza: insights from seasonal epidemics in Wisconsin, 1967–2004. Influenza and Other Respiratory Viruses 4(4), 205–212.\r\n\r\n\r\n\r\nBackground  Influenza infections pose a serious burden of illness in the United States. We explored age, influenza strains, and seasonal epidemic curves in relation to influenza-associated mortality.\r\n\r\n\r\n\r\nMethods  The state of Wisconsin death records for the years 1967–2004 were analyzed for three distinct populations: children, general population, and elderly. Yearly parameters of duration, intensity, and peak timing were obtained from Annual Harmonic Regression coefficients.\r\n\r\n\r\n\r\nResults  Overall, elderly had the highest rate and intensity of influenza mortality. The children and infant subpopulations showed an earlier and wider range in duration of peak timing than elderly. During A/Hong Kong/1/68 pandemic years, the elderly subpopulation showed no change in mortality rates while a sharp increase was observed for the children and infant subpopulations. In epidemic years such as 1966–1969, children and infants showed a dramatic decrease in the severity of influenza outbreaks over time. The elderly had increased baseline mortality in years (1986–1987) where predominant strain was characterized as A/Singapore/6/86.\r\n\r\n\r\n\r\nConclusions  Our findings indicate that the younger populations may have benefited from the lack of a major shift in viral strains for a number of decades. Furthermore, we demonstrate considerable heterogeneity in the spread of seasonal influenza across age categories, with implications both for the modeling of influenza seasonality, risk assessment, and effective distribution and timing of vaccine and prophylactic interventions.","publicationCount":0,"publicationCountByYear":[],"citationCnt":6,"citationCountByYear":[],"rank":20994.0,"entityType":0},"dataVersion":"2019-01-11-prod"}