{"entityType":2,"citedByExpression":"RId=2599047341","relatedPaperExpression":"Or(Id=811784610,Id=2057324758,Id=2767743075,Id=2034343718,Id=2770679673,Id=2553005652,Id=2729901515,Id=2761944849,Id=322295744,Id=2317017690,Id=2037057575,Id=2048595284,Id=2770362465,Id=2049657713,Id=2558997796,Id=2777491903,Id=2460340851,Id=2044538842,Id=2042793394,Id=2521643211,Id=811784610,Id=2057324758,Id=2767743075,Id=2034343718,Id=2770679673,Id=2553005652,Id=2729901515,Id=2761944849,Id=322295744,Id=2317017690,Id=2037057575,Id=2048595284,Id=2770362465,Id=2049657713,Id=2558997796,Id=2777491903,Id=2460340851,Id=2044538842,Id=2042793394,Id=2521643211,Id=811784610,Id=2057324758,Id=2767743075,Id=2034343718,Id=2770679673,Id=2553005652,Id=2729901515,Id=2761944849,Id=322295744,Id=2317017690,Id=2037057575,Id=2048595284,Id=2770362465,Id=2049657713,Id=2558997796,Id=2777491903,Id=2460340851,Id=2044538842,Id=2042793394,Id=2521643211,Id=811784610,Id=2057324758,Id=2767743075,Id=2034343718,Id=2770679673,Id=2553005652,Id=2729901515,Id=2761944849,Id=322295744,Id=2317017690,Id=2037057575,Id=2048595284,Id=2770362465,Id=2049657713,Id=2558997796,Id=2777491903,Id=2460340851,Id=2044538842,Id=2042793394,Id=2521643211)","paperReferencesExpression":"Or(Id=2121745948,Id=2173251738,Id=2063700061,Id=1973776704,Id=1970020090,Id=1482932425,Id=2097817223,Id=1993378799,Id=1997547618,Id=2008544706,Id=1991394861,Id=2072000799,Id=1519793694,Id=2738516213,Id=2429674000,Id=2066355812,Id=2095837545,Id=2175912711,Id=1985864871,Id=2058978736,Id=2162506906)","entityExpression":"Id=2599047341","entity":{"fieldsOfStudy":[{"authorCount":0,"id":121332964,"displayName":"Physics","description":"","publicationCount":0,"publicationCountByYear":[],"citationCnt":0,"citationCountByYear":[],"rank":0.0,"entityType":0},{"authorCount":0,"id":50335755,"displayName":"Phenomenon","description":"","publicationCount":0,"publicationCountByYear":[],"citationCnt":0,"citationCountByYear":[],"rank":1.0,"entityType":0},{"authorCount":0,"id":166566181,"displayName":"Natural disaster","description":"","publicationCount":0,"publicationCountByYear":[],"citationCnt":0,"citationCountByYear":[],"rank":2.0,"entityType":0},{"authorCount":0,"id":61586570,"displayName":"Magnitude (mathematics)","description":"","publicationCount":0,"publicationCountByYear":[],"citationCnt":0,"citationCountByYear":[],"rank":3.0,"entityType":0},{"authorCount":0,"id":986699,"displayName":"El Niño","description":"","publicationCount":0,"publicationCountByYear":[],"citationCnt":0,"citationCountByYear":[],"rank":4.0,"entityType":0},{"authorCount":0,"id":49204034,"displayName":"Climatology","description":"","publicationCount":0,"publicationCountByYear":[],"citationCnt":0,"citationCountByYear":[],"rank":5.0,"entityType":0}],"venueInfo":{"id":148121101,"entityType":3,"displayName":"New Journal of Physics","volume":"20","issue":"4","firstPage":"43036","lastPage":"","publishedDate":"2018-04-16T00:00:00Z","doi":"10.1088/1367-2630/aabb25"},"sources":[{"sourceType":3,"link":"http://arxiv.org/pdf/1703.09138.pdf"},{"sourceType":1,"link":"https://arxiv.org/abs/1703.09138"},{"sourceType":1,"link":"http://iopscience.iop.org/article/10.1088/1367-2630/aabb25"}],"authors":[{"currentInstitution":{"authorCount":0,"latitude":0.0,"longitude":0.0,"id":13955877,"displayName":"Bar-Ilan University","description":"","publicationCount":0,"publicationCountByYear":[],"citationCnt":0,"citationCountByYear":[],"rank":0.0,"entityType":0},"institutions":[{"authorCount":0,"latitude":0.0,"longitude":0.0,"id":13955877,"displayName":"Bar-Ilan University","description":"","publicationCount":0,"publicationCountByYear":[],"citationCnt":0,"citationCountByYear":[],"rank":0.0,"entityType":0},{"authorCount":0,"latitude":0.0,"longitude":0.0,"id":124227911,"displayName":"Ben-Gurion University of the Negev","description":"","publicationCount":0,"publicationCountByYear":[],"citationCnt":0,"citationCountByYear":[],"rank":0.0,"entityType":0}],"coAuthorCount":0,"hIndex":0.0,"id":2516733500,"displayName":"Jun Meng","description":"","publicationCount":0,"publicationCountByYear":[],"citationCnt":0,"citationCountByYear":[],"rank":0.0,"entityType":0},{"currentInstitution":{"authorCount":0,"latitude":0.0,"longitude":0.0,"id":13955877,"displayName":"Bar-Ilan University","description":"","publicationCount":0,"publicationCountByYear":[],"citationCnt":0,"citationCountByYear":[],"rank":0.0,"entityType":0},"institutions":[{"authorCount":0,"latitude":0.0,"longitude":0.0,"id":13955877,"displayName":"Bar-Ilan University","description":"","publicationCount":0,"publicationCountByYear":[],"citationCnt":0,"citationCountByYear":[],"rank":0.0,"entityType":0},{"authorCount":0,"latitude":0.0,"longitude":0.0,"id":124227911,"displayName":"Ben-Gurion University of the Negev","description":"","publicationCount":0,"publicationCountByYear":[],"citationCnt":0,"citationCountByYear":[],"rank":0.0,"entityType":0}],"coAuthorCount":0,"hIndex":0.0,"id":2182939817,"displayName":"Jingfang Fan","description":"","publicationCount":0,"publicationCountByYear":[],"citationCnt":0,"citationCountByYear":[],"rank":0.0,"entityType":0},{"currentInstitution":{"authorCount":0,"latitude":0.0,"longitude":0.0,"id":124227911,"displayName":"Ben-Gurion University of the Negev","description":"","publicationCount":0,"publicationCountByYear":[],"citationCnt":0,"citationCountByYear":[],"rank":0.0,"entityType":0},"institutions":[{"authorCount":0,"latitude":0.0,"longitude":0.0,"id":124227911,"displayName":"Ben-Gurion University of the Negev","description":"","publicationCount":0,"publicationCountByYear":[],"citationCnt":0,"citationCountByYear":[],"rank":0.0,"entityType":0}],"coAuthorCount":0,"hIndex":0.0,"id":2050239695,"displayName":"Yosef Ashkenazy","description":"","publicationCount":0,"publicationCountByYear":[],"citationCnt":0,"citationCountByYear":[],"rank":0.0,"entityType":0},{"currentInstitution":{"authorCount":0,"latitude":0.0,"longitude":0.0,"id":200763008,"displayName":"University of Giessen","description":"","publicationCount":0,"publicationCountByYear":[],"citationCnt":0,"citationCountByYear":[],"rank":0.0,"entityType":0},"institutions":[{"authorCount":0,"latitude":0.0,"longitude":0.0,"id":200763008,"displayName":"University of Giessen","description":"","publicationCount":0,"publicationCountByYear":[],"citationCnt":0,"citationCountByYear":[],"rank":0.0,"entityType":0}],"coAuthorCount":0,"hIndex":0.0,"id":219989508,"displayName":"Armin Bunde","description":"","publicationCount":0,"publicationCountByYear":[],"citationCnt":0,"citationCountByYear":[],"rank":0.0,"entityType":0},{"currentInstitution":{"authorCount":0,"latitude":0.0,"longitude":0.0,"id":13955877,"displayName":"Bar-Ilan University","description":"","publicationCount":0,"publicationCountByYear":[],"citationCnt":0,"citationCountByYear":[],"rank":0.0,"entityType":0},"institutions":[{"authorCount":0,"latitude":0.0,"longitude":0.0,"id":13955877,"displayName":"Bar-Ilan University","description":"","publicationCount":0,"publicationCountByYear":[],"citationCnt":0,"citationCountByYear":[],"rank":0.0,"entityType":0},{"authorCount":0,"latitude":0.0,"longitude":0.0,"id":114531698,"displayName":"Tokyo Institute of Technology","description":"","publicationCount":0,"publicationCountByYear":[],"citationCnt":0,"citationCountByYear":[],"rank":0.0,"entityType":0}],"coAuthorCount":0,"hIndex":0.0,"id":630663198,"displayName":"Shlomo Havlin","description":"","publicationCount":0,"publicationCountByYear":[],"citationCnt":0,"citationCountByYear":[],"rank":0.0,"entityType":0}],"totalAuthorCount":5,"referenceCount":21,"references":[2121745948,2173251738,2063700061,1973776704,1970020090,1482932425,2097817223,1993378799,1997547618,2008544706,1991394861,2072000799,1519793694,2738516213,2429674000,2066355812,2095837545,2175912711,1985864871,2058978736,2162506906],"relatedPapers":[811784610,2057324758,2767743075,2034343718,2770679673,2553005652,2729901515,2761944849,322295744,2317017690,2037057575,2048595284,2770362465,2049657713,2558997796,2777491903,2460340851,2044538842,2042793394,2521643211,811784610,2057324758,2767743075,2034343718,2770679673,2553005652,2729901515,2761944849,322295744,2317017690,2037057575,2048595284,2770362465,2049657713,2558997796,2777491903,2460340851,2044538842,2042793394,2521643211,811784610,2057324758,2767743075,2034343718,2770679673,2553005652,2729901515,2761944849,322295744,2317017690,2037057575,2048595284,2770362465,2049657713,2558997796,2777491903,2460340851,2044538842,2042793394,2521643211,811784610,2057324758,2767743075,2034343718,2770679673,2553005652,2729901515,2761944849,322295744,2317017690,2037057575,2048595284,2770362465,2049657713,2558997796,2777491903,2460340851,2044538842,2042793394,2521643211],"publicationType":"1","paperResources":[],"id":2599047341,"displayName":"Forecasting the magnitude and onset of El Niño based on climate network","description":"El Nino is probably the most influential climate phenomenon on interannual time scales. It affects the global climate system and is associated with natural disasters and serious consequences in many aspects of human life. However, the forecasting of the onset and in particular the magnitude of El Nino are still not accurate, at least more than half a year in advance. Here, we introduce a new forecasting index based on network links representing the similarity of low frequency temporal temperature anomaly variations between different sites in the El Nino 3.4 region. We find that significant upward trends and peaks in this index forecast with high accuracy both the onset and magnitude of El Nino approximately 1 year ahead. The forecasting procedure we developed improves in particular the prediction of the magnitude of El Nino and is validated based on several, up to more than a century long, datasets.","publicationCount":0,"publicationCountByYear":[],"citationCnt":3,"citationCountByYear":[],"rank":20600.0,"entityType":0},"dataVersion":"2019-01-11-prod"}