{"entityType":1,"citedByExpression":"Join(RId,Composite(AA.AuId=1198578353))","publicationsExpression":"Composite(AA.AuId=1198578353)","entityExpression":"Id=1198578353","entity":{"currentInstitution":{"authorCount":0,"latitude":0.0,"longitude":0.0,"id":157536573,"displayName":"Pasteur Institute","description":"","publicationCount":0,"publicationCountByYear":[],"citationCnt":0,"citationCountByYear":[],"rank":0.0,"entityType":0},"fieldsOfStudy":[{"authorCount":0,"id":86803240,"description":"","publicationCount":0,"publicationCountByYear":[],"citationCnt":0,"citationCountByYear":[],"rank":0.0,"entityType":0},{"authorCount":0,"id":18903297,"description":"","publicationCount":0,"publicationCountByYear":[],"citationCnt":0,"citationCountByYear":[],"rank":1.0,"entityType":0},{"authorCount":0,"id":2776290222,"description":"","publicationCount":0,"publicationCountByYear":[],"citationCnt":0,"citationCountByYear":[],"rank":2.0,"entityType":0},{"authorCount":0,"id":60644358,"description":"","publicationCount":0,"publicationCountByYear":[],"citationCnt":0,"citationCountByYear":[],"rank":3.0,"entityType":0},{"authorCount":0,"id":33923547,"description":"","publicationCount":0,"publicationCountByYear":[],"citationCnt":0,"citationCountByYear":[],"rank":4.0,"entityType":0},{"authorCount":0,"id":50318809,"description":"","publicationCount":0,"publicationCountByYear":[],"citationCnt":0,"citationCountByYear":[],"rank":5.0,"entityType":0},{"authorCount":0,"id":126255220,"description":"","publicationCount":0,"publicationCountByYear":[],"citationCnt":0,"citationCountByYear":[],"rank":6.0,"entityType":0},{"authorCount":0,"id":177142836,"description":"","publicationCount":0,"publicationCountByYear":[],"citationCnt":0,"citationCountByYear":[],"rank":7.0,"entityType":0},{"authorCount":0,"id":549774020,"description":"","publicationCount":0,"publicationCountByYear":[],"citationCnt":0,"citationCountByYear":[],"rank":8.0,"entityType":0},{"authorCount":0,"id":2781087480,"description":"","publicationCount":0,"publicationCountByYear":[],"citationCnt":0,"citationCountByYear":[],"rank":9.0,"entityType":0},{"authorCount":0,"id":2781407068,"description":"","publicationCount":0,"publicationCountByYear":[],"citationCnt":0,"citationCountByYear":[],"rank":10.0,"entityType":0},{"authorCount":0,"id":8891405,"description":"","publicationCount":0,"publicationCountByYear":[],"citationCnt":0,"citationCountByYear":[],"rank":11.0,"entityType":0},{"authorCount":0,"id":9760119,"description":"","publicationCount":0,"publicationCountByYear":[],"citationCnt":0,"citationCountByYear":[],"rank":12.0,"entityType":0},{"authorCount":0,"id":11804247,"description":"","publicationCount":0,"publicationCountByYear":[],"citationCnt":0,"citationCountByYear":[],"rank":13.0,"entityType":0},{"authorCount":0,"id":150194340,"description":"","publicationCount":0,"publicationCountByYear":[],"citationCnt":0,"citationCountByYear":[],"rank":14.0,"entityType":0},{"authorCount":0,"id":2775905019,"description":"","publicationCount":0,"publicationCountByYear":[],"citationCnt":0,"citationCountByYear":[],"rank":15.0,"entityType":0},{"authorCount":0,"id":31258907,"description":"","publicationCount":0,"publicationCountByYear":[],"citationCnt":0,"citationCountByYear":[],"rank":16.0,"entityType":0},{"authorCount":0,"id":41008148,"description":"","publicationCount":0,"publicationCountByYear":[],"citationCnt":0,"citationCountByYear":[],"rank":17.0,"entityType":0},{"authorCount":0,"id":83849155,"description":"","publicationCount":0,"publicationCountByYear":[],"citationCnt":0,"citationCountByYear":[],"rank":18.0,"entityType":0},{"authorCount":0,"id":105339364,"description":"","publicationCount":0,"publicationCountByYear":[],"citationCnt":0,"citationCountByYear":[],"rank":19.0,"entityType":0}],"coAuthorCount":23,"hIndex":0.0,"publicationsQueryExpression":"Composite(AA.AuId=1198578353)","id":1198578353,"displayName":"Slimane Ben Miled","description":"","publicationCount":7,"publicationCountByYear":[{"count":3,"year":2015},{"count":1,"year":2014},{"count":1,"year":2010},{"count":1,"year":2009},{"count":1,"year":2006}],"citationCnt":15,"citationCountByYear":[{"count":4,"year":2018},{"count":2,"year":2017},{"count":3,"year":2016},{"count":4,"year":2015},{"count":1,"year":2014},{"count":1,"year":2013}],"websites":[],"rank":-18.597,"entityType":0},"dataVersion":"2019-01-11-prod"}