{"entityType":1,"citedByExpression":"Join(RId,Composite(AA.AuId=2309764913))","publicationsExpression":"Composite(AA.AuId=2309764913)","entityExpression":"Id=2309764913","entity":{"currentInstitution":{"authorCount":0,"latitude":0.0,"longitude":0.0,"id":125687163,"displayName":"City College of New York","description":"","publicationCount":0,"publicationCountByYear":[],"citationCnt":0,"citationCountByYear":[],"rank":0.0,"entityType":0},"fieldsOfStudy":[{"authorCount":0,"id":73555534,"description":"","publicationCount":0,"publicationCountByYear":[],"citationCnt":0,"citationCountByYear":[],"rank":0.0,"entityType":0},{"authorCount":0,"id":87040749,"description":"","publicationCount":0,"publicationCountByYear":[],"citationCnt":0,"citationCountByYear":[],"rank":1.0,"entityType":0},{"authorCount":0,"id":125932096,"description":"","publicationCount":0,"publicationCountByYear":[],"citationCnt":0,"citationCountByYear":[],"rank":2.0,"entityType":0},{"authorCount":0,"id":162324750,"description":"","publicationCount":0,"publicationCountByYear":[],"citationCnt":0,"citationCountByYear":[],"rank":3.0,"entityType":0},{"authorCount":0,"id":22679943,"description":"","publicationCount":0,"publicationCountByYear":[],"citationCnt":0,"citationCountByYear":[],"rank":4.0,"entityType":0},{"authorCount":0,"id":149782125,"description":"","publicationCount":0,"publicationCountByYear":[],"citationCnt":0,"citationCountByYear":[],"rank":5.0,"entityType":0},{"authorCount":0,"id":158739034,"description":"","publicationCount":0,"publicationCountByYear":[],"citationCnt":0,"citationCountByYear":[],"rank":6.0,"entityType":0},{"authorCount":0,"id":199539241,"description":"","publicationCount":0,"publicationCountByYear":[],"citationCnt":0,"citationCountByYear":[],"rank":7.0,"entityType":0},{"authorCount":0,"id":2777016058,"description":"","publicationCount":0,"publicationCountByYear":[],"citationCnt":0,"citationCountByYear":[],"rank":8.0,"entityType":0},{"authorCount":0,"id":2779060202,"description":"","publicationCount":0,"publicationCountByYear":[],"citationCnt":0,"citationCountByYear":[],"rank":9.0,"entityType":0},{"authorCount":0,"id":2779731175,"description":"","publicationCount":0,"publicationCountByYear":[],"citationCnt":0,"citationCountByYear":[],"rank":10.0,"entityType":0},{"authorCount":0,"id":83864248,"description":"","publicationCount":0,"publicationCountByYear":[],"citationCnt":0,"citationCountByYear":[],"rank":11.0,"entityType":0},{"authorCount":0,"id":136264566,"description":"","publicationCount":0,"publicationCountByYear":[],"citationCnt":0,"citationCountByYear":[],"rank":12.0,"entityType":0},{"authorCount":0,"id":154611951,"description":"","publicationCount":0,"publicationCountByYear":[],"citationCnt":0,"citationCountByYear":[],"rank":13.0,"entityType":0},{"authorCount":0,"id":34947359,"description":"","publicationCount":0,"publicationCountByYear":[],"citationCnt":0,"citationCountByYear":[],"rank":14.0,"entityType":0},{"authorCount":0,"id":121332964,"description":"","publicationCount":0,"publicationCountByYear":[],"citationCnt":0,"citationCountByYear":[],"rank":15.0,"entityType":0},{"authorCount":0,"id":26873012,"description":"","publicationCount":0,"publicationCountByYear":[],"citationCnt":0,"citationCountByYear":[],"rank":16.0,"entityType":0},{"authorCount":0,"id":40636538,"description":"","publicationCount":0,"publicationCountByYear":[],"citationCnt":0,"citationCountByYear":[],"rank":17.0,"entityType":0},{"authorCount":0,"id":118615104,"description":"","publicationCount":0,"publicationCountByYear":[],"citationCnt":0,"citationCountByYear":[],"rank":18.0,"entityType":0},{"authorCount":0,"id":68532491,"description":"","publicationCount":0,"publicationCountByYear":[],"citationCnt":0,"citationCountByYear":[],"rank":19.0,"entityType":0}],"coAuthorCount":10,"hIndex":0.0,"publicationsQueryExpression":"Composite(AA.AuId=2309764913)","id":2309764913,"displayName":"Hernán D. Rozenfeld","description":"","publicationCount":9,"publicationCountByYear":[{"count":2,"year":2011},{"count":3,"year":2010},{"count":3,"year":2009},{"count":1,"year":2008}],"citationCnt":695,"citationCountByYear":[{"count":8,"year":2019},{"count":81,"year":2018},{"count":96,"year":2017},{"count":83,"year":2016},{"count":102,"year":2015},{"count":79,"year":2014},{"count":82,"year":2013},{"count":93,"year":2012},{"count":37,"year":2011},{"count":16,"year":2010},{"count":14,"year":2009},{"count":2,"year":2008},{"count":2,"year":2007}],"websites":[],"rank":-17.039,"entityType":0},"dataVersion":"2019-01-11-prod"}