{"entityType":1,"citedByExpression":"Join(RId,Composite(AA.AuId=2548704101))","publicationsExpression":"Composite(AA.AuId=2548704101)","entityExpression":"Id=2548704101","entity":{"currentInstitution":{"authorCount":0,"latitude":0.0,"longitude":0.0,"id":16391192,"displayName":"Tel Aviv University","description":"","publicationCount":0,"publicationCountByYear":[],"citationCnt":0,"citationCountByYear":[],"rank":0.0,"entityType":0},"fieldsOfStudy":[{"authorCount":0,"id":162324750,"description":"","publicationCount":0,"publicationCountByYear":[],"citationCnt":0,"citationCountByYear":[],"rank":0.0,"entityType":0},{"authorCount":0,"id":119857082,"description":"","publicationCount":0,"publicationCountByYear":[],"citationCnt":0,"citationCountByYear":[],"rank":1.0,"entityType":0},{"authorCount":0,"id":154945302,"description":"","publicationCount":0,"publicationCountByYear":[],"citationCnt":0,"citationCountByYear":[],"rank":2.0,"entityType":0},{"authorCount":0,"id":107826830,"description":"","publicationCount":0,"publicationCountByYear":[],"citationCnt":0,"citationCountByYear":[],"rank":3.0,"entityType":0}],"coAuthorCount":3,"hIndex":0.0,"publicationsQueryExpression":"Composite(AA.AuId=2548704101)","id":2548704101,"displayName":"Nimrod Serok","description":"","publicationCount":2,"publicationCountByYear":[{"count":1,"year":2018},{"count":1,"year":2015}],"citationCnt":2,"citationCountByYear":[{"count":1,"year":2018},{"count":1,"year":2017}],"websites":[],"rank":-20.179,"entityType":0},"dataVersion":"2019-01-11-prod"}