{"entityType":1,"citedByExpression":"Join(RId,Composite(AA.AuId=2794470509))","publicationsExpression":"Composite(AA.AuId=2794470509)","entityExpression":"Id=2794470509","entity":{"currentInstitution":{"authorCount":0,"latitude":0.0,"longitude":0.0,"id":111088046,"displayName":"Boston University","description":"","publicationCount":0,"publicationCountByYear":[],"citationCnt":0,"citationCountByYear":[],"rank":0.0,"entityType":0},"fieldsOfStudy":[{"authorCount":0,"id":99844830,"description":"","publicationCount":0,"publicationCountByYear":[],"citationCnt":0,"citationCountByYear":[],"rank":0.0,"entityType":0},{"authorCount":0,"id":121332964,"description":"","publicationCount":0,"publicationCountByYear":[],"citationCnt":0,"citationCountByYear":[],"rank":1.0,"entityType":0},{"authorCount":0,"id":87040749,"description":"","publicationCount":0,"publicationCountByYear":[],"citationCnt":0,"citationCountByYear":[],"rank":2.0,"entityType":0},{"authorCount":0,"id":106159729,"description":"","publicationCount":0,"publicationCountByYear":[],"citationCnt":0,"citationCountByYear":[],"rank":3.0,"entityType":0},{"authorCount":0,"id":33923547,"description":"","publicationCount":0,"publicationCountByYear":[],"citationCnt":0,"citationCountByYear":[],"rank":4.0,"entityType":0},{"authorCount":0,"id":105795698,"description":"","publicationCount":0,"publicationCountByYear":[],"citationCnt":0,"citationCountByYear":[],"rank":5.0,"entityType":0},{"authorCount":0,"id":26873012,"description":"","publicationCount":0,"publicationCountByYear":[],"citationCnt":0,"citationCountByYear":[],"rank":6.0,"entityType":0},{"authorCount":0,"id":62520636,"description":"","publicationCount":0,"publicationCountByYear":[],"citationCnt":0,"citationCountByYear":[],"rank":7.0,"entityType":0},{"authorCount":0,"id":143691341,"description":"","publicationCount":0,"publicationCountByYear":[],"citationCnt":0,"citationCountByYear":[],"rank":8.0,"entityType":0},{"authorCount":0,"id":121194460,"description":"","publicationCount":0,"publicationCountByYear":[],"citationCnt":0,"citationCountByYear":[],"rank":9.0,"entityType":0},{"authorCount":0,"id":134306372,"description":"","publicationCount":0,"publicationCountByYear":[],"citationCnt":0,"citationCountByYear":[],"rank":10.0,"entityType":0},{"authorCount":0,"id":197055811,"description":"","publicationCount":0,"publicationCountByYear":[],"citationCnt":0,"citationCountByYear":[],"rank":11.0,"entityType":0},{"authorCount":0,"id":118918019,"description":"","publicationCount":0,"publicationCountByYear":[],"citationCnt":0,"citationCountByYear":[],"rank":12.0,"entityType":0},{"authorCount":0,"id":186603090,"description":"","publicationCount":0,"publicationCountByYear":[],"citationCnt":0,"citationCountByYear":[],"rank":13.0,"entityType":0},{"authorCount":0,"id":2780388253,"description":"","publicationCount":0,"publicationCountByYear":[],"citationCnt":0,"citationCountByYear":[],"rank":14.0,"entityType":0},{"authorCount":0,"id":114350782,"description":"","publicationCount":0,"publicationCountByYear":[],"citationCnt":0,"citationCountByYear":[],"rank":15.0,"entityType":0},{"authorCount":0,"id":74650414,"description":"","publicationCount":0,"publicationCountByYear":[],"citationCnt":0,"citationCountByYear":[],"rank":16.0,"entityType":0},{"authorCount":0,"id":102289811,"description":"","publicationCount":0,"publicationCountByYear":[],"citationCnt":0,"citationCountByYear":[],"rank":17.0,"entityType":0},{"authorCount":0,"id":2776012548,"description":"","publicationCount":0,"publicationCountByYear":[],"citationCnt":0,"citationCountByYear":[],"rank":18.0,"entityType":0},{"authorCount":0,"id":2778312390,"description":"","publicationCount":0,"publicationCountByYear":[],"citationCnt":0,"citationCountByYear":[],"rank":19.0,"entityType":0}],"coAuthorCount":37,"hIndex":0.0,"publicationsQueryExpression":"Composite(AA.AuId=2794470509)","id":2794470509,"displayName":"Youngki Lee","description":"","publicationCount":30,"publicationCountByYear":[{"count":2,"year":2004},{"count":2,"year":2003},{"count":1,"year":2002},{"count":5,"year":2001},{"count":6,"year":2000},{"count":7,"year":1999},{"count":5,"year":1998},{"count":2,"year":1996}],"citationCnt":1377,"citationCountByYear":[{"count":2,"year":2019},{"count":55,"year":2018},{"count":76,"year":2017},{"count":79,"year":2016},{"count":47,"year":2015},{"count":74,"year":2014},{"count":78,"year":2013},{"count":86,"year":2012},{"count":98,"year":2011},{"count":64,"year":2010},{"count":72,"year":2009},{"count":65,"year":2008},{"count":97,"year":2007},{"count":77,"year":2006},{"count":52,"year":2005},{"count":86,"year":2004},{"count":74,"year":2003},{"count":82,"year":2002},{"count":52,"year":2001},{"count":33,"year":2000},{"count":28,"year":1999}],"websites":[],"rank":-16.061,"entityType":0},"dataVersion":"2019-01-11-prod"}